pitertools/__init__.py
pitertools/map_async.py
pitertools/map_executor.py
pitertools/map_parallel.py
pitertools/map_threaded.py
pitertools/py.typed
pitertools-0.7.0.dist-info/METADATA
pitertools-0.7.0.dist-info/WHEEL
pitertools-0.7.0.dist-info/licenses/LICENSE
pitertools-0.7.0.dist-info/RECORD
