Metadata-Version: 2.4
Name: pitertools
Version: 0.7.0
Author-email: tsah <tsah.weiss@gmail.com>
License-File: LICENSE
Requires-Python: >=3.8.0
Provides-Extra: dev
Requires-Dist: ipython>=8.9.0; extra == 'dev'
Requires-Dist: pytest; extra == 'dev'
Requires-Dist: ruff; extra == 'dev'
